seanalgorithms4/__init__.py
seanalgorithms4/readfile.py
seanalgorithms4/algorithms4_practice/__init__.py
seanalgorithms4/algorithms4_practice/readme.py
seanalgorithms4/algorithms4_practice/test.py
seanalgorithms4/algorithms4_practice/digital_image_processing_X/__init__.py
seanalgorithms4/algorithms4_practice/digital_image_processing_X/change_contrast.py
seanalgorithms4/algorithms4_practice/digital_image_processing_X/test_digital_image_processing.py
seanalgorithms4/algorithms4_practice/digital_image_processing_X/edge_detection/__init__.py
seanalgorithms4/algorithms4_practice/digital_image_processing_X/edge_detection/canny.py
seanalgorithms4/algorithms4_practice/digital_image_processing_X/filters/__init__.py
seanalgorithms4/algorithms4_practice/digital_image_processing_X/filters/convolve.py
seanalgorithms4/algorithms4_practice/digital_image_processing_X/filters/gaussian_filter.py
seanalgorithms4/algorithms4_practice/digital_image_processing_X/filters/median_filter.py
seanalgorithms4/algorithms4_practice/digital_image_processing_X/filters/sobel_filter.py
seanalgorithms4/algorithms4_practice/maths/3n+1.py
seanalgorithms4/algorithms4_practice/maths/__init__.py
seanalgorithms4/algorithms4_practice/maths/abs.py
seanalgorithms4/algorithms4_practice/maths/abs_max.py
seanalgorithms4/algorithms4_practice/maths/abs_min.py
seanalgorithms4/algorithms4_practice/maths/average_mean.py
seanalgorithms4/algorithms4_practice/maths/average_median.py
seanalgorithms4/algorithms4_practice/maths/basic_maths.py
seanalgorithms4/algorithms4_practice/maths/binary_exponentiation.py
seanalgorithms4/algorithms4_practice/maths/collatz_sequence.py
seanalgorithms4/algorithms4_practice/maths/extended_euclidean_algorithm.py
seanalgorithms4/algorithms4_practice/maths/factorial_python.py
seanalgorithms4/algorithms4_practice/maths/factorial_recursive.py
seanalgorithms4/algorithms4_practice/maths/fermat_little_theorem.py
seanalgorithms4/algorithms4_practice/maths/fibonacci.py
seanalgorithms4-0.3.dist-info/LICENSE
seanalgorithms4-0.3.dist-info/METADATA
seanalgorithms4-0.3.dist-info/WHEEL
seanalgorithms4-0.3.dist-info/top_level.txt
seanalgorithms4-0.3.dist-info/RECORD
