Metadata-Version: 2.1
Name: seanalgorithms4
Version: 0.3
Summary: Python algorithms4
Home-page: https://github.com/seanlab3/algorithms4
Author: seanlab
Author-email: seanlabcoding33@gmail.com
License: UNKNOWN
Platform: UNKNOWN
Classifier: License :: OSI Approved :: MIT License
Requires-Dist: cython
